setup.py
funcomp/__init__.py
funcomp/tests.py
funcomp.egg-info/PKG-INFO
funcomp.egg-info/SOURCES.txt
funcomp.egg-info/dependency_links.txt
funcomp.egg-info/not-zip-safe
funcomp.egg-info/top_level.txt