Metadata-Version: 1.0
Name: funcomp
Version: 1.0
Summary: Function composition is simple.
Home-page: UNKNOWN
Author: Bence Faludi
Author-email: bence@ozmo.hu
License: GPL
Platform: UNKNOWN
